autoflix_cli/__init__.py
autoflix_cli/anilist.py
autoflix_cli/cli_utils.py
autoflix_cli/config_loader.py
autoflix_cli/defaults.py
autoflix_cli/history_ui.py
autoflix_cli/main.py
autoflix_cli/player_manager.py
autoflix_cli/proxy.py
autoflix_cli/tracker.py
autoflix_cli/handlers/__init__.py
autoflix_cli/handlers/anilist.py
autoflix_cli/handlers/anime_sama.py
autoflix_cli/handlers/coflix.py
autoflix_cli/handlers/french_stream.py
autoflix_cli/handlers/playback.py
autoflix_cli/handlers/wiflix.py
autoflix_cli/scraping/__init__.py
autoflix_cli/scraping/anime_sama.py
autoflix_cli/scraping/coflix.py
autoflix_cli/scraping/deobfuscate.py
autoflix_cli/scraping/french_stream.py
autoflix_cli/scraping/objects.py
autoflix_cli/scraping/player.py
autoflix_cli/scraping/utils.py
autoflix_cli/scraping/wiflix.py
autoflix_cli-0.4.8.dist-info/METADATA
autoflix_cli-0.4.8.dist-info/WHEEL
autoflix_cli-0.4.8.dist-info/entry_points.txt
autoflix_cli-0.4.8.dist-info/licenses/LICENSE
autoflix_cli-0.4.8.dist-info/RECORD
