Metadata-Version: 2.4
Name: autoflix-cli
Version: 0.4.8
Summary: Stream movies, series, and anime in French (VF & VOSTFR) directly from your terminal. Inspired by ani-cli.
Project-URL: Homepage, https://github.com/PaulExplorer/autoflix-cli
Project-URL: Repository, https://github.com/PaulExplorer/autoflix-cli.git
Author: PaulExplorer
License: MIT
License-File: LICENSE
Keywords: VF,VOSTFR,anime,autoflix,movies,series
Requires-Python: >=3.9.2
Requires-Dist: beautifulsoup4>=4.14.3
Requires-Dist: curl-cffi>=0.13.0
Requires-Dist: flask>=3.1.2
Requires-Dist: html5lib>=1.1
Requires-Dist: jsbeautifier>=1.15.4
Requires-Dist: m3u8>=6.0.0
Requires-Dist: platformdirs>=4.0.0
Requires-Dist: pycryptodome>=3.23.0
Requires-Dist: readchar>=4.2.1
Requires-Dist: rich>=14.2.0
